{"mc":{
	"101014_idle_3_1":{
		"frameRate":6,
		"labels":[
			{"name":"101014_idle_3_1","frame":1,"end":6}
			
			],
		"events":[
			
			],
		"frames":[
			
			{
			"res":"3-00000",
			"x":-36,
			"y":-149
			},
			{
			"res":"3-00001",
			"x":-37,
			"y":-148
			},
			{
			"res":"3-00002",
			"x":-38,
			"y":-146
			},
			{
			"res":"3-00003",
			"x":-38,
			"y":-145
			},
			{
			"res":"3-00004",
			"x":-38,
			"y":-146
			},
			{
			"res":"3-00005",
			"x":-36,
			"y":-148
			}
			]
}},
	"res":{
		"3-00003":{"x":71,"y":0,"w":70,"h":129},
		"3-00002":{"x":0,"y":0,"w":71,"h":129},
		"3-00004":{"x":0,"y":129,"w":69,"h":130},
		"3-00001":{"x":141,"y":0,"w":69,"h":130},
		"3-00005":{"x":69,"y":129,"w":68,"h":130},
		"3-00000":{"x":137,"y":130,"w":67,"h":129}
	}}